nonebot_plugin_fakepic/__init__.py
nonebot_plugin_fakepic/__main__.py
nonebot_plugin_fakepic/config.py
nonebot_plugin_fakepic/draw.py
nonebot_plugin_fakepic/resourse/bot_icon.png
nonebot_plugin_fakepic/resourse/level_icon.png
nonebot_plugin_fakepic-0.2.2.dist-info/LICENSE
nonebot_plugin_fakepic-0.2.2.dist-info/METADATA
nonebot_plugin_fakepic-0.2.2.dist-info/WHEEL
nonebot_plugin_fakepic-0.2.2.dist-info/RECORD
