Metadata-Version: 2.1
Name: nonebot-plugin-fakepic
Version: 0.2.2
Summary: A nonebot plugin for fake chat screenshots
Home-page: https://github.com/lm175/nonebot-plugin-fakepic
License: MIT
Author: lm175
Author-email: 17736762488@163.com
Requires-Python: >=3.10,<4.0
Classifier: License :: OSI Approved :: MIT License
Classifier: Programming Language :: Python :: 3
Classifier: Programming Language :: Python :: 3.10
Classifier: Programming Language :: Python :: 3.11
Classifier: Programming Language :: Python :: 3.12
Classifier: Programming Language :: Python :: 3.13
Requires-Dist: httpx (>=0.27.0)
Requires-Dist: nonebot-adapter-onebot (>=2.3.1)
Requires-Dist: nonebot2 (>=2.3.2)
Requires-Dist: pil_utils (==0.1.10)
